{
  "inference_patterns": [
    {
      "input": "What is 2+2?",
      "basic_response": {
        "text": "2 + 2 equals 4.",
        "structured": null
      },
      "parameterized_response": {
        "text": "2 + 2 equals 4.",
        "structured": null
      }
    },
    {
      "input": "Explain quantum computing",
      "basic_response": {
        "text": "Quantum computing is a type of computing that leverages the principles of quantum mechanics to process information in fundamentally different ways than classical computing. Here are the key concepts and principles that define quantum computing:\n\n### 1. **Quantum Bits (Qubits):**\n   - In classical computing, the basic unit of information is the bit, which can be either a 0 or a 1. In quantum computing, the basic unit is the quantum bit or qubit. A qubit can exist in a state of 0, 1, or both simultaneously due to a property called superposition.\n\n### 2. **Superposition:**\n   - Superposition allows qubits to perform multiple calculations at once. When a qubit is in superposition, it can represent both 0 and 1 simultaneously, which enables quantum computers to process a vast amount of information in parallel.\n\n### 3. **Entanglement:**\n   - Entanglement is a quantum phenomenon where qubits become interconnected in such a way that the state of one qubit can depend on the state of another, no matter the distance between them. This property allows for coordinated operations on qubits, which can enhance the computational power of quantum systems.\n\n### 4. **Quantum Gates:**\n   - Quantum gates are the basic building blocks of quantum circuits, analogous to classical logic gates. They manipulate qubits through operations that change their states, allowing for complex computations. Quantum gates can create superpositions and entangled states.\n\n### 5. **Quantum Algorithms:**\n   - Quantum computing can solve certain problems more efficiently than classical computing. Notable quantum algorithms include:\n     - **Shor's Algorithm:** Efficiently factors large integers, which has implications for cryptography.\n     - **Grover's Algorithm:** Provides a quadratic speedup for unstructured search problems.\n\n### 6. **Decoherence:**\n   - Quantum states are fragile and can be disturbed by their environment, leading to a loss of information known as decoherence. Quantum computers must implement error correction and noise reduction techniques to maintain the integrity of qubit states during computation.\n\n### 7. **Quantum Supremacy:**\n   - This term refers to the point at which a quantum computer can perform a calculation that is practically impossible for classical computers to achieve in a reasonable time. Google claimed to have achieved quantum supremacy in 2019 with their Sycamore processor.\n\n### 8. **Applications:**\n   - Quantum computing has potential applications across various fields, including:\n     - Cryptography (breaking existing encryption methods)\n     - Drug discovery and material science (simulating molecular interactions)\n     - Optimization problems (solving complex logistical challenges)\n     - Machine learning (enhancing algorithms and speeding up computations)\n\n### 9. **Current State and Challenges:**\n   - As of now, quantum computing is still in a developmental stage. Researchers are working on building scalable quantum computers, improving qubit coherence times, and developing practical quantum algorithms. Challenges include error correction, qubit connectivity, and the physical realization of qubits (using superconductors, trapped ions, etc.).\n\nIn summary, quantum computing represents a revolutionary shift in how we think about computation, with the potential to solve certain problems much more efficiently than classical computers. However, the field is still evolving, and significant challenges remain before quantum computers can be widely and reliably used.",
        "structured": null
      },
      "parameterized_response": {
        "text": "Quantum computing is a field of computing that harnesses the principles of quantum mechanics to process information in fundamentally different ways than classical computing. Here\u2019s an overview of the key concepts and components of quantum computing:\n\n### 1. **Classical vs. Quantum Bits**\n- **Classical Bits**: In classical computing, the basic unit of information is the bit, which can be either 0 or 1. Classical computers manipulate these bits using logical operations.\n- **Quantum Bits (Qubits)**: In quantum computing, the basic unit of information is the qubit. A qubit can exist in a state of 0, 1, or both simultaneously due to a property called superposition. This allows quantum computers to represent and process a vast amount of information concurrently.\n\n### 2. **Superposition**\n- Superposition is a fundamental principle of quantum mechanics that allows qubits to be in multiple states at once. For instance, a qubit can be in a state that is a combination of 0 and 1, which can be mathematically represented as a linear combination of the two states. This property enables quantum computers to explore many possible solutions simultaneously.\n\n### 3. **Entanglement**\n- Entanglement is another quantum phenomenon where qubits become interconnected in such a way that the state of one qubit can depend on the state of another, regardless of the distance between them. Entangled qubits can provide a powerful resource for quantum computing, enabling complex correlations that classical bits cannot achieve.\n\n### 4. **Quantum Gates**\n- Quantum gates are the quantum analogs of classical logic gates. They manipulate qubits through operations that change their states. Quantum gates can perform operations such as rotation and entanglement, allowing quantum algorithms to be constructed. The combination of multiple gates forms a quantum circuit.\n\n### 5. **Quantum Algorithms**\n- Quantum algorithms leverage the unique properties of qubits to solve problems more efficiently than classical algorithms. Some well-known quantum algorithms include:\n  - **Shor\u2019s Algorithm**: Efficiently factors large integers, which has implications for cryptography.\n  - **Grover\u2019s Algorithm**: Provides a quadratic speedup for unstructured search problems.\n  - **Quantum Simulation**: Simulating quantum systems, which is particularly useful in fields like chemistry and materials science.\n\n### 6. **Decoherence and Error Correction**\n- Quantum systems are highly sensitive to their environment, and interactions with the environment can lead to decoherence, which destroys the quantum state of qubits. Quantum error correction techniques are essential to maintain the integrity of quantum information over time and ensure reliable computations.\n\n### 7. **Quantum Hardware**\n- Various physical implementations of quantum computers exist, including:\n  - **Superconducting Qubits**: Use superconducting circuits to create and manipulate qubits.\n  - **Trapped Ions**: Use ions trapped in electromagnetic fields to represent qubits.\n  - **Topological Qubits**: Utilize exotic particles called anyons to create qubits that are more robust against errors.\n  \n### 8. **Applications of Quantum Computing**\n- Quantum computing has potential applications in various fields, including:\n  - Cryptography: Breaking classical encryption schemes and creating secure communication channels.\n  - Optimization: Solving complex optimization problems in logistics, finance, and machine learning.\n  - Drug Discovery: Simulating molecular interactions to discover new drugs more efficiently.\n\n### Conclusion\nQuantum computing represents a paradigm shift in how we think about computation. While still in its early stages, with ongoing research and development, it holds the promise of solving problems that are currently intractable for classical computers, potentially revolutionizing various industries and scientific fields.",
        "structured": null
      }
    },
    {
      "input": "Write a haiku about AI",
      "basic_response": {
        "text": "Silent circuits hum,  \nWisdom woven in the code,  \nDreams of thought arise.",
        "structured": null
      },
      "parameterized_response": {
        "text": "Silicon whispers,  \nDreams of logic intertwine,  \nFuture's spark ignites.",
        "structured": null
      }
    }
  ]
}